[
  {
    "subject": "PORT",
    "number": "1101",
    "title": "Elementary Portuguese 1",
    "scheduleType": "Lecture",
    "credits": 4,
    "nuPath": [],
    "sections": [
      { "term": "202310", "crn": "11439" },
      { "term": "202330", "crn": "30005" }
    ],
    "description": "Begins the integrated development of elementary language skills through cultural exploration. Includes class discussion and project-based learning. Offers students an opportunity to gain a deeper understanding of daily life, social norms, and family structure in Portuguese-speaking countries.Designed for students with very little or no prior knowledge of Portuguese.",
    "coreqs": [],
    "prereqs": []
  },
  {
    "subject": "PORT",
    "number": "1102",
    "title": "Elementary Portuguese 2",
    "scheduleType": "Lecture",
    "credits": 4,
    "nuPath": [],
    "sections": [
      { "term": "202310", "crn": "11754" },
      { "term": "202330", "crn": "30022" }
    ],
    "description": "Builds on PORT 1101 and continues the integrated development of elementary language skills through cultural exploration. Includes class discussion and project-based learning. Offers students an opportunity to gain a deeper understanding of the linguistic, cultural, and geographic diversity of the Portuguese-speaking world.",
    "coreqs": [],
    "prereqs": [
      { "subject": "PORT", "number": "1101" },
      "Or",
      { "subject": "PORT", "number": "1301" }
    ]
  },
  {
    "subject": "PORT",
    "number": "1501",
    "title": "Accelerated Elementary Portuguese 1",
    "scheduleType": "Lecture",
    "credits": 4,
    "nuPath": [],
    "sections": [{ "term": "202330", "crn": "38100" }],
    "description": "Introduces Portuguese to native/heritage speakers of Spanish, beginner-level heritage speakers of Portuguese, and students who have completed at least two levels of intermediate Spanish. Focuses on fundamental communication skills—speaking, aural comprehension, reading, and writing. Also explores cultural elements of the Portuguese-speaking countries. Students who do not have the preparation described may seek permission of instructor. This course is the equivalent of completing two semesters of elementary Portuguese.",
    "coreqs": [],
    "prereqs": []
  },
  {
    "subject": "PORT",
    "number": "2101",
    "title": "Intermediate Portuguese 1",
    "scheduleType": "Lecture",
    "credits": 4,
    "nuPath": [],
    "sections": [
      { "term": "202310", "crn": "14162" },
      { "term": "202330", "crn": "34757" }
    ],
    "description": "Builds on PORT 1102 and begins the integrated development of intermediate language skills through cultural exploration. Includes class discussion and project-based learning. Offers students an opportunity to gain a deeper understanding of the changes to modern life in Portuguese-speaking countries and efforts to face societal challenges.",
    "coreqs": [],
    "prereqs": [
      { "subject": "PORT", "number": "1102" },
      "Or",
      { "subject": "PORT", "number": "1302" }
    ]
  },
  {
    "subject": "PORT",
    "number": "2102",
    "title": "Intermediate Portuguese 2",
    "scheduleType": "Lecture",
    "credits": 4,
    "nuPath": ["WI"],
    "sections": [
      { "term": "202310", "crn": "20244" },
      { "term": "202330", "crn": "34758" }
    ],
    "description": "Builds on PORT 2101 and focuses on further development of vocabulary. Offers students an opportunity to continue to master grammar and conversation through written composition, prepared oral reports, and reading and discussion from contemporary Portuguese materials.",
    "coreqs": [],
    "prereqs": [
      "(",
      { "subject": "PORT", "number": "2101" },
      "Or",
      { "subject": "PORT", "number": "2301" },
      ")",
      "And",
      "(",
      { "subject": "ENGL", "number": "1111" },
      "Or",
      { "subject": "ENGL", "number": "1102" },
      "Or",
      { "subject": "ENGW", "number": "1111" },
      "Or",
      { "subject": "ENGW", "number": "1102" },
      ")"
    ]
  }
]
